pipen_cli_run/__init__.py
pipen_cli_run/entry.py
pipen_cli_run/version.py
pipen_cli_run-1.0.2.dist-info/METADATA
pipen_cli_run-1.0.2.dist-info/WHEEL
pipen_cli_run-1.0.2.dist-info/entry_points.txt
pipen_cli_run-1.0.2.dist-info/RECORD
